adilib/__init__.py
adilib/converter.py
adilib/d2.py
adilib/dag.py
adilib/entity_dag.py
adilib/experiment_yaml.py
adilib/frictionless.py
adilib/html.py
adilib/log_formats.py
adilib/owl.py
adilib/parse_reference.py
adilib/reference_count_summary.py
adilib/schema_source_validation.py
adilib/sql.py
adilib/tree_resolver.py
adilib/yaml.py
adilib/scripts/__init__.py
adilib/scripts/adi_build.py
adilib/scripts/adi_build_sql.py
adilib/templates/__init__.py
adilib/templates/create_db.sql.jinja
adilib/templates/entities_alphabetical.html.jinja
adilib/templates/main_overview_docs.html.jinja
adilib/templates/properties_alphabetical.html.jinja
adilib/templates/schema.d2.jinja
adilib/templates/schema.owl.jinja
adilib/templates/values.html.jinja
adilib-1.0.1.dist-info/METADATA
adilib-1.0.1.dist-info/WHEEL
adilib-1.0.1.dist-info/entry_points.txt
adilib-1.0.1.dist-info/top_level.txt
adilib-1.0.1.dist-info/RECORD
