Metadata-Version: 2.1
Name: adilib
Version: 1.0.1
Summary: Application Data Interface (ADI) library
Author-email: James Mathews <mathewj2@mskcc.org>
Project-URL: Documentation, https://adiframework.com
Requires-Python: >=3.7
Requires-Dist: pandas ==2.2.2
Requires-Dist: Jinja2 ==3.1.2
Requires-Dist: toml ==0.10.2
Requires-Dist: oyaml ==1.0
